datajoint/__init__.py
datajoint/admin.py
datajoint/attribute_adapter.py
datajoint/autopopulate.py
datajoint/blob.py
datajoint/cli.py
datajoint/condition.py
datajoint/connection.py
datajoint/declare.py
datajoint/dependencies.py
datajoint/diagram.py
datajoint/errors.py
datajoint/expression.py
datajoint/external.py
datajoint/fetch.py
datajoint/hash.py
datajoint/heading.py
datajoint/jobs.py
datajoint/logging.py
datajoint/plugin.py
datajoint/preview.py
datajoint/s3.py
datajoint/schemas.py
datajoint/settings.py
datajoint/table.py
datajoint/user_tables.py
datajoint/utils.py
datajoint/version.py
datajoint-0.14.6.dist-info/licenses/LICENSE.txt
datajoint-0.14.6.dist-info/METADATA
datajoint-0.14.6.dist-info/WHEEL
datajoint-0.14.6.dist-info/entry_points.txt
datajoint-0.14.6.dist-info/top_level.txt
datajoint-0.14.6.dist-info/RECORD
