Metadata-Version: 2.4
Name: datajoint
Version: 0.14.6
Summary: DataJoint for Python is a framework for scientific workflow management based on relational principles. DataJoint is built on the foundation of the relational data model and prescribes a consistent method for organizing, populating, computing, and querying data.
Author: Raphael Guzman, Edgar Walker
Author-email: Dimitri Yatsenko <dimitri@datajoint.com>, Thinh Nguyen <thinh@datajoint.com>, DataJoint Contributors <support@datajoint.com>
Maintainer-email: Dimitri Yatsenko <dimitri@datajoint.com>, DataJoint Contributors <support@datajoint.com>
License:  GNU LESSER GENERAL PUBLIC LICENSE
Project-URL: Homepage, https://docs.datajoint.com/
Project-URL: Documentation, https://docs.datajoint.com/
Project-URL: Repository, https://github.com/datajoint/datajoint-python
Project-URL: Bug Tracker, https://github.com/datajoint/datajoint-python/issues
Project-URL: Release Notes, https://github.com/datajoint/datajoint-python/releases
Keywords: database,automated,automation,compute,data,pipeline,workflow,scientific,science,research,neuroscience,bioinformatics,bio-informatics,datajoint
Classifier: Programming Language :: Python
Classifier: Development Status :: 5 - Production/Stable
Classifier: Intended Audience :: Science/Research
Classifier: Intended Audience :: Healthcare Industry
Classifier: License :: OSI Approved :: GNU Lesser General Public License v2 or later (LGPLv2+)
Classifier: Topic :: Software Development :: Libraries :: Python Modules
Classifier: Topic :: Scientific/Engineering
Classifier: Topic :: Scientific/Engineering :: Bio-Informatics
Classifier: Topic :: Scientific/Engineering :: Artificial Intelligence
Requires-Python: <4.0,>=3.9
License-File: LICENSE.txt
Requires-Dist: numpy
Requires-Dist: pymysql>=0.7.2
Requires-Dist: deepdiff
Requires-Dist: pyparsing
Requires-Dist: ipython
Requires-Dist: pandas
Requires-Dist: tqdm
Requires-Dist: networkx
Requires-Dist: pydot
Requires-Dist: minio>=7.0.0
Requires-Dist: matplotlib
Requires-Dist: otumat
Requires-Dist: faker
Requires-Dist: cryptography
Requires-Dist: urllib3
Requires-Dist: setuptools
Provides-Extra: test
Requires-Dist: pytest; extra == "test"
Requires-Dist: pytest-cov; extra == "test"
Provides-Extra: dev
Requires-Dist: pre-commit; extra == "dev"
Requires-Dist: black==24.2.0; extra == "dev"
Requires-Dist: flake8; extra == "dev"
Requires-Dist: isort; extra == "dev"
Requires-Dist: codespell; extra == "dev"
Requires-Dist: pytest; extra == "dev"
Requires-Dist: pytest-cov; extra == "dev"
Dynamic: license-file
